base/__init__.py
base/amqp_sdk.py
base/amqp_thread_safe.py
base/common.py
base/config.py
base/device.py
base/logger.py
base/message.py
base/mongo_db.py
base/postgres_client.py
base/redis_db.py
base/api/__init__.py
base/api/api.py
base/api/api_log.py
base/api/rate_limiter.py
base/api/swagger_constructor.py
shared_beta_devoerjg-0.0.1.dist-info/licenses/LICENSE
shared_beta_devoerjg-0.0.1.dist-info/METADATA
shared_beta_devoerjg-0.0.1.dist-info/WHEEL
shared_beta_devoerjg-0.0.1.dist-info/top_level.txt
shared_beta_devoerjg-0.0.1.dist-info/RECORD
