Metadata-Version: 2.4
Name: shared-beta_devoerjg
Version: 0.0.1
Summary: Internal utilities for MongoDB, Redis, and other services
Author-email: zhengpingzhu <ZHENGPING.ZHU@deltaww.com>
License: MIT
Project-URL: Homepage, https://corecode.deltaww.com/iot-team/utility/shared/edge-shared
Project-URL: Bug Tracker, https://corecode.deltaww.com/iot-team/utility/shared/edge-shared
Classifier: Programming Language :: Python :: 3
Classifier: License :: OSI Approved :: MIT License
Classifier: Operating System :: OS Independent
Requires-Python: >=3.7
License-File: LICENSE
Requires-Dist: blinker==1.6.2
Requires-Dist: certifi==2023.5.7
Requires-Dist: charset-normalizer==3.1.0
Requires-Dist: click==8.1.4
Requires-Dist: colorama==0.4.6
Requires-Dist: dnspython==2.3.0
Requires-Dist: exceptiongroup==1.1.2
Requires-Dist: Flask==2.3.2
Requires-Dist: idna==3.4
Requires-Dist: iniconfig==2.0.0
Requires-Dist: itsdangerous==2.1.2
Requires-Dist: Jinja2==3.1.4
Requires-Dist: MarkupSafe==2.1.3
Requires-Dist: packaging==23.1
Requires-Dist: pluggy==1.2.0
Requires-Dist: pymongo==4.4.0
Requires-Dist: pytest==7.4.0
Requires-Dist: PyYAML==6.0
Requires-Dist: requests==2.31.0
Requires-Dist: tomli==2.0.1
Requires-Dist: urllib3==2.0.3
Requires-Dist: Werkzeug==2.3.6
Requires-Dist: psycopg2-binary==2.9.9
Dynamic: license-file
